<annotation><filename>5c61f6a6-901a-414a-baec-3c32a093227e.jpg</filename><source><database>Unknown</database></source><size><width>910</width><height>512</height><depth>3</depth></size><segmented>0</segmented><object><name>fist</name><pose>Unspecified</pose><truncated>0</truncated><difficult>0</difficult><bndbox><xmin>341</xmin><ymin>146</ymin><xmax>380</xmax><ymax>185</ymax></bndbox></object><object><name>no_gesture</name><pose>Unspecified</pose><truncated>0</truncated><difficult>0</difficult><bndbox><xmin>537</xmin><ymin>375</ymin><xmax>562</xmax><ymax>428</ymax></bndbox></object></annotation>