<annotation><filename>f1e1bccd-72c3-4388-a62c-da47e8ac124a.jpg</filename><source><database>Unknown</database></source><size><width>683</width><height>512</height><depth>3</depth></size><segmented>0</segmented><object><name>peace</name><pose>Unspecified</pose><truncated>0</truncated><difficult>0</difficult><bndbox><xmin>239</xmin><ymin>218</ymin><xmax>287</xmax><ymax>309</ymax></bndbox></object><object><name>no_gesture</name><pose>Unspecified</pose><truncated>0</truncated><difficult>0</difficult><bndbox><xmin>370</xmin><ymin>441</ymin><xmax>422</xmax><ymax>493</ymax></bndbox></object></annotation>